{
  "source_file": "ressources/compte-rendu-50-2003.Zeendoc.pdf",
  "total_pages": 8,
  "total_images": 1,
  "document_annotation": "{\n  \"language\": \"fr\",\n  \"title\": \"Compte rendu 50\",\n  \"document_type\": \"procès-verbal\",\n  \"summary\": \"Le document est un compte rendu de la Commission Internationale de Numismatique pour l'année 2003. Il inclut des informations sur la composition du bureau, les statuts et la constitution de la commission, des hommages à des numismates notables, l'histoire des collections numismatiques, une nécrologie, des comptes rendus de réunions, et des informations sur les membres de la commission.\",\n  \"key_points\": [\n    \"Composition du Bureau de la Commission Internationale de Numismatique.\",\n    \"Statuts et Constitution de la Commission Internationale de Numismatique.\",\n    \"Hommages à Karl Pink et Ivan G. Spassky.\",\n    \"Histoire des collections numismatiques, notamment la collection de la Alpha Bank à Athènes.\",\n    \"Nécrologie de Laura Breglia.\",\n    \"Comptes rendus des réunions du Bureau à Madrid en mars et septembre 2003.\",\n    \"Comptes de la Commission et Assemblée générale.\",\n    \"Liste des membres de la Commission, y compris les institutions et les membres honoraires.\",\n    \"Informations sur la bourse annuelle de la CIN.\"\n  ],\n  \"authors\": [\n    \"Commission Internationale de Numismatique\"\n  ],\n  \"date\": \"2003\",\n  \"organizations\": [\n    \"Commission Internationale de Numismatique\",\n    \"Comité International des Sciences Historiques\",\n    \"Museo Arqueológico Nacional\",\n    \"Harvard University Art Museums\",\n    \"National Museum of Finland\",\n    \"Hunerian Museum\",\n    \"Kunsthistorisches Museum\",\n    \"State Puskhin Museum of Fine Arts\"\n  ]\n}",
  "markdown_files": [
    "page_1.md",
    "page_2.md",
    "page_3.md",
    "page_4.md",
    "page_5.md",
    "page_6.md",
    "page_7.md",
    "page_8.md"
  ],
  "images": [
    {
      "id": "img-0.jpeg",
      "filename": "page2_img1.jpg",
      "page": 2,
      "position": {
        "top_left_x": 400,
        "top_left_y": 355,
        "bottom_right_x": 788,
        "bottom_right_y": 734
      },
      "annotation": "{\n  \"image_type\": \"logo\",\n  \"title\": \"Logo CN\",\n  \"short_description\": \"Logo représentant les initiales 'CN' avec une globe terrestre\",\n  \"detailed_description\": \"Le logo est principalement composé de deux grandes lettres 'C' et 'N' entrelacées. À l'intérieur de la lettre 'N', il y a une représentation stylisée d'un globe terrestre en noir et blanc. Le design est simple mais distinctif, suggérant une organisation ou une entreprise avec une portée ou une influence mondiale.\",\n  \"data_extracted\": \"\"\n}"
    }
  ]
}